Workbook

Sheet NFR questions
A1: Non-functional requirements: questions to answer with numbers
A2: Emergency drug delivery to a ship or port by UAV system, Russian Arctic (Team 5). Fill in the yellow cells. See the Legend sheet for how.
A4: ID | B4: Question | C4: Unit | D4: Comes from (OA element) | E4: Type | F4: Key driver | G4: Value | H4: Source / justification | I4: Status
A5: A | B5: Demand and response time (OAB-1: emergency report → decision)
A6: A1 | B6: How many delivery requests per year must the system handle? | C6: requests/year | D6: Emergency report | E6: Fact | G6: 300 | H6: Ships: about 1 in 5 divert each year for medical reasons, which gives tens of cases in the sector. Add urgent drugs and samples for fields, ports and settlements, about 5 a week. Assumed; check with FMBA and Glavsevmorput. | I6: Assumed
A7: A2 | B7: How many missions may run at the same time at peak? | C7: missions | D7: Emergency report | E7: Target | G7: 3 | H7: 3 covers the backlog after a bad-weather window, about one per base area. | I7: Open
A8: A3 | B8: What share of requests go to ships at sea (rest: ports and shore sites)? | C8: % | D8: OC1.1 / OC1.2 | E8: Fact | G8: 0.3 | I8: Open
A9: A4 | B9: What is the maximum time from emergency report to medicine in the crew's hands? | C9: h | D9: Whole OAB-1 chain | E9: Target | F9: ★ | G9: 4 | H9: ≤ 3 h for fixed sites (C1 ≤ 200 km) ≤ 5 h for ships at sea (C2 ≤ 300 km, moving target): Must clearly beat a helicopter (hours, weather-limited, >1M RUB) and diversion (days). It covers the critical first hours for antibiotics and antidotes. | I9: Open
A10: A5 | B10: What is the maximum time from delivery request to departure? | C10: min | D10: Delivery request → Transport | E10: Target | G10: 45 | H10: Medical decision by radio ~15–20 min, then preparation and approval in parallel ~25–30 min | I10: Open
A11: B | B11: Payload (OAB-1: Prepare medicine package → Medicine package)
A12: B1 | B12: What is the maximum payload mass per delivery? | C12: kg | D12: Medicine package | E12: Target | F12: ★ | G12: 3 | H12: A drug or test kit is 0.5–2 kg, plus an insulated cold-chain box. Benchmarks: Zipline ~1.8 kg, Matternet M2 2 kg. At Russian Post’s 13,600 RUB/kg, that’s still ~40k RUB per flight. | I12: Open
A13: B2 | B13: What are the maximum package dimensions? | C13: cm × cm × cm | D13: Medicine package | E13: Target | G13: 35 × 25 × 20 | H13: Fits an insulated medical carrier with a 3 kg load. | I13: Open
A14: B3 | B14: What temperature range must the package keep inside? | C14: °C | D14: Medicine package | E14: Fact | G14: + 2…+8 °C never below 0 °C | H14: +2…+8 °C is the standard range for vaccines, insulin and samples. In the Arctic the real risk is freezing, not overheating. | I14: Open
A15: B4 | B15: For how long must the package hold that temperature? | C15: h | D15: Medicine package (at least A4) | E15: Derived | G15: 6 | H15: A4 (4 h) plus 50% margin for waiting on deck or a delayed handover. | I15: Open
A16: B5 | B16: What maximum shock may the package experience? | C16: g | D16: Medicine package (samples) | E16: Fact | G16: ≤ 10 g | H16: Protects glass vials and sample tubes. It allows a soft winch or parachute handover and rules out free fall. Assumed; check with the pharmacy or lab. | I16: Open
A17: C | B17: Distance and coverage (OAB-1: Transport package to the site)
A18: C1 | B18: What is the maximum distance from a base to a fixed site (port, field)? | C18: km | D18: OC1.1, DRM-1/3 | E18: Fact | G18: 200 | H18: From the nearest base on map 2: Prirazlomnoye 49 km, Arctic LNG 2 87, Messoyakha 127, Bovanenkovo 165. Novy Port (~270 km) has its own airfield and terminal, so it’s left out. | I18: Open
A19: C2 | B19: What is the maximum distance from a base to a ship at sea? | C19: km | D19: OC1.2, DRM-2 | E19: Target | F19: ★ | G19: 300 | H19: Ships on the Kara Sea track are 190–340 km from the bases (Dikson → track 188 km, Sabetta → track 256 km). 300 covers most of it. | I19: Open
A20: C3 | B20: What is the maximum speed of a target ship? | C20: knots | D20: OC1.2 (moving target) | E20: Fact | I20: Open
A21: C4 | B21: What is the maximum transit time? (calculated: A4 − A5 − E4) | C21: h | D21: A4 minus preparation and handover | E21: Derived | G21: =IF(COUNT(G9,G10,G36)<3,"",G9-G10/60-G36/60) | H21: Calculated from A4, A5 and E4; do not type here | I21: Open
A22: C5 | B22: What length of route or area must be covered? | C22: km / km² | D22: Maps 1–2 | E22: Target | G22: 1500 km | H22: The NSR track Kara Gates → Dikson (~900 km) plus the Ob Bay lane to Sabetta (~350 km), and the onshore Yamal–Gydan cluster. | I22: Open
A23: C6 | B23: What is the largest gap between existing sites along the covered route? | C23: km | D23: Map 2 | E23: Fact | G23: 380 | H23: The largest gap between existing sites along that route is Sabetta ↔ Dikson. The others are shorter: Varandey–Amderma ~180, Amderma–Kharasavey ~250, Kharasavey–Sabetta ~190. | I23: Open
A24: D | B24: Operating environment (Weather in which delivery must still work)
A25: D1 | B25: What is the operating temperature range? | C25: °C | D25: Arctic climate | E25: Fact | F25: ★ | G25: -40...+20 С | H25: The Northern Sea Route Handbook reports winter temperatures of approximately −30 to −40 °C and summer temperatures occasionally exceeding +20 °C. The proposed range reflects Arctic operating conditions. | I25: Open
A26: D2 | B26: What is the maximum sustained wind for operation? | C26: m/s | D26: Arctic climate | E26: Fact | F26: ★ | G26: 15 m/s | H26: Proposed design target for strong Arctic winds. For comparison, the DJI FlyCart 30 has a maximum wind resistance of 12 m/s, while the aOrion Heli-E specifies wind resistance around 15–16 m/s. The target requires UAV-specific verification. | I26: Open
A27: D3 | B27: What is the maximum gust? | C27: m/s | D27: Arctic climate | E27: Fact | G27: 20 m/s | H27: Preliminary engineering target for short-duration gusts, selected to provide a margin above the 15 m/s sustained-wind requirement. Not validated by the cited UAV specifications; feasibility must be confirmed. | I27: Open
A28: D4 | B28: What is the minimum visibility and cloud ceiling for operation? | C28: m / m | D28: Fog, snow | E28: Fact | G28: Visibility ≥ 1000m cloud ceiling ≥ 150m | H28: Preliminary operational limits. Arctic marine fog and low clouds are common along the Northern Sea Route. Exact flight minima must be validated against the selected UAV, navigation system, and applicable aviation regulations. | I28: Open
A29: D5 | B29: What share of missions happen in darkness (polar night)? | C29: % | D29: Season | E29: Fact | G29: 50% of missions | H29: Preliminary planning assumption for missions conducted in darkness. Polar night and strong seasonal daylight variations occur at Arctic latitudes. The actual percentage must be calculated from mission locations, dates, and expected demand. | I29: Open
A30: D6 | B30: What is the highest latitude of operation? | C30: °N | D30: Route (navigation and comms) | E30: Fact | G30: 80° N | H30: Proposed geographical coverage limit. Northern Sea Route waters include high-latitude passages such as Vilkitsky Strait, reaching approximately 77.8° N. The 80° N limit provides a geographical margin for operations | I30: Open
A31: D7 | B31: On what share of days per year must the service be available? | C31: % of days | D31: Customer expectation vs weather statistics | E31: Target | F31: ★ | G31: ≥ 90% of days/year | H31: Proposed service availability target for emergency medical delivery. This is a stakeholder-driven requirement, not a measured Arctic weather statistic. Achievability must be assessed using regional weather records and operational constraints. | I31: Open
A32: E | B32: Handover at the receiving site (OAB-1: Medicine package → Receive and confirm package)
A33: E1 | B33: What free area can a typical receiving site provide (ship deck, port pad)? | C33: m × m | D33: Receiving Site | E33: Fact | G33: 5 × 5 m | H33: Proposed minimum clear receiving area on the ship deck for winch delivery. DJI FlyCart 30 demonstrates cargo delivery without landing, using a 20 m winch cable. The 5 × 5 m area is a preliminary safety requirement, not a manufacturer specification | I33: Open
A34: E2 | B34: What maximum ship motion must handover tolerate? | C34: roll °, heave m | D34: OC1.2 | E34: Fact | F34: ★ | G34: Roll ≤ ±5° heave ≤ ±0.5 m | H34: Preliminary limits for ship motion during package transfer. Deck movement affects payload positioning and safe touchdown. These limits must be validated through vessel-motion analysis and winch delivery tests; they are not established by the DJI specifications. | I34: Open
A35: E3 | B35: What delivery position accuracy is required? | C35: m | D35: Receive and confirm package | E35: Target | G35: ≤ 1 m | H35: Proposed maximum package placement error relative to the designated receiving point. DJI FlyCart 30 specifies RTK hovering accuracy of ±0.1 m under strong GNSS conditions, but this does not guarantee 1 m package placement accuracy on a moving ship. Additional compensation for wind and vessel motion is required. | I35: Open
A36: E4 | B36: What is the maximum handover time at the site? | C36: min | D36: Receive and confirm package | E36: Target | G36: ≤ 5 min | H36: Proposed maximum handover time, including positioning, lowering, release and confirmation. DJI FlyCart 30 supports a maximum winch speed of 0.8 m/s and a 20 m cable, making a short transfer technically plausible. The complete 5-minute target requires operational validation. | I36: Open
A37: E5 | B37: What is the maximum delay for the delivery confirmation to reach the coordinator? | C37: min | D37: Delivery confirmation | E37: Target | G37: ≤ 2 min | H37: Proposed maximum delay between successful package receipt and confirmation to the ground coordinator. This is a system-level communication requirement selected for emergency medical delivery, not a value taken from UAV specifications. | I37: Open
A38: F | B38: Weather data (OAB-2: Collect → Process → Use in forecasts)
A39: F1 | B39: What range and accuracy are needed for temperature? | C39: °C, ±°C | D39: Weather observations | E39: Target | G39: −50 to +30 °C; ±1 °C | H39: Proposed temperature data range covering the Arctic operating environment (D1: −40 to +20 °C) with an additional 10 °C margin. The accuracy is a preliminary engineering target. | I39: Open
A40: F2 | B40: What range and accuracy are needed for pressure? | C40: hPa, ±hPa | D40: Weather observations | E40: Target | G40: 900–1100 hPa; ±1 hPa | H40: Proposed atmospheric pressure measurement range and accuracy for weather monitoring and flight planning. The range covers typical sea-level pressure variations with additional margin. | I40: Open
A41: F3 | B41: What range and accuracy are needed for wind speed and direction? | C41: m/s ±, ° ± | D41: Weather observations | E41: Target | G41: 0–40 m/s; ±1 m/s; direction ±10° | H41: Proposed wind measurement range exceeding the UAV operating limits (D2: 15 m/s sustained wind; D3: 20 m/s gusts). The additional range allows the system to detect unsafe wind conditions. | I41: Open
A42: F4 | B42: What range and accuracy are needed for visibility? | C42: m, ±% | D42: Weather observations | E42: Target | G42: 0–20,000 m; ±10% | H42: Proposed visibility data range and accuracy. Visibility information supports flight planning and go/no-go decisions under Arctic fog and snow conditions. | I42: Open
A43: F5 | B43: How often must measurements be taken? | C43: per s or per km | D43: Weather observations | E43: Target | G43: Every 60 s | H43: Proposed update interval for local weather observations to detect rapidly changing conditions. Actual availability depends on the selected sensors and weather service. | I43: Open
A44: F6 | B44: What altitude range must observations cover? | C44: m | D44: Weather observations | E44: Target | G44: 0–500 m above sea level | H44: Proposed vertical coverage of weather observations for low-altitude UAV operations. This range must be adjusted after defining the UAV flight altitude. | I44: Open
A45: F7 | B45: What is the maximum delay from measurement to delivery to the meteorological service? | C45: min | D45: Weather data | E45: Target | G45: ≤ 2 min | H45: Proposed maximum delay between weather measurement and its availability to the meteorological service. This is a data-latency requirement, not a confirmed capability of Arctic weather networks. | I45: Open
A46: G | B46: Monitoring and communication (OAB-1: Delivery plan, status in flight)
A47: G1 | B47: What share of the mission distance must have a communication link? | C47: % | D47: Transport package | E47: Target | G47: ≥ 95 | H47: BVLOS flight needs a near-continuous C2 link; gaps are covered by an autonomous failsafe (return / hold). Ties to the “loss of communication” risk. Depends on the chosen link (radio + satellite relay) | I47: Open
A48: G2 | B48: What is the maximum interval between status updates in flight? | C48: s | D48: Status to operator | E48: Target | G48: ≤ 10 | H48: Telemetry at 1 Hz is typical, but a satellite link in the Arctic allows ~10 s. Needed for the operator’s go/abort decision | I48: Open
A49: G3 | B49: What navigation position accuracy is required en route? | C49: m | D49: Delivery plan | E49: Target | G49: ≤ 5 (95%, horizontal) | H49: Multi-constellation GNSS (GPS + GLONASS; GLONASS handles high latitudes better). Handover precision (E3, ≤ 1 m) is a separate requirement and is achieved by local sensors. | I49: Open
A50: H | B50: Readiness and maintenance (OAB-3: Supply → Maintain → Readiness status)
A51: H1 | B51: What share of time must the system be ready to launch? | C51: % | D51: Readiness status | E51: Target | G51: ≥ 95 | H51: Technical readiness excluding weather. Consistent with D7 (≥ 90% days/year including weather no-go). | I51: Open
A52: H2 | B52: What is the maximum turnaround time between missions? | C52: min | D52: Readiness status | E52: Target | G52: ≤ 30 | H52: Battery swap or warm-up, loading a new container, pre-flight checks. Cold batteries need preheating. | I52: Open
A53: H3 | B53: What is the minimum time between failures? | C53: flight hours | D53: Maintain and calibrate equipment | E53: Target | G53: ≥ 100 | H53: Target level for an industrial UAV at concept stage; to be refined from the chosen platform’s data. | I53: Open
A54: H4 | B54: What is the maximum time to repair at a base? | C54: h | D54: Maintain and calibrate equipment | E54: Target | G54: ≤ 24 | H54: Replacement of line-replaceable units (LRUs) at the base without sending the UAV out for repair. Quick swap of the winch and battery ≤ 4 h. | I54: Open
A55: H5 | B55: What resupply interval for spare parts must the system survive? | C55: days | D55: Spare parts and services | E55: Fact | G55: 90 | H55: Arctic port supply is seasonal (navigation season, ice, air only in winter), so a spare-parts kit sized for 90 days. This is a Fact type, so confirm with the port/operator stakeholders. | I55: Open
A56: H6 | B56: What service life is required? | C56: years | D56: Invest in the service | E56: Target | G56: 7 | H56: Airframe and electronics; batteries and the winch are consumables replaced by cycle count (~300–500 cycles). | I56: Open
A57: I | B57: Safety and regulation (OAB-4: Permits, Operating rules, Concerns)
A58: I1 | B58: What is the minimum mission success rate? | C58: % | D58: OC1 | E58: Target | G58: ≥ 95 | H58: Of the missions launched after go/no-go. Success means delivered, drug integrity kept, delivery within the allowed time (E4, E5). | I58: Open
A59: I2 | B59: What is the maximum acceptable probability of harm to people per flight hour? | C59: 1/h | D59: Concerns, Operating rules | E59: Rule | G59: ≤ 1·10⁻⁶ | H59: Common target for ground risk in UAS safety methodology (JARUS SORA / EASA). Over water the main exposure is the crew at handover and the port zone. | I59: Open
A60: I3 | B60: What is the maximum allowed flight altitude in the corridor? | C60: m | D60: Operating rules | E60: Rule | G60: 150 (AGL) | H60: Working ceiling in the corridor; keeps flight below manned aviation and in the lower wind layer. | I60: Open
A61: I4 | B61: What is the minimum distance from people and facilities, except at handover? | C61: m | D61: Operating rules | E61: Rule | G61: ≥ 50 | H61: Margin over the common 30 m separation from uninvolved people, accounting for gusts up to 20 m/s. | I61: Open
A62: I5 | B62: What is the maximum noise at the receiving site or settlement? | C62: dB | D62: Concerns | E62: Rule | G62: ≤ 55 dBA day / ≤ 45 dBA night | H62: At the settlement boundary, per Russian sanitary norms for residential areas (SanPiN). For ships there is no such limit, and emergency flights can have an exception. | I62: Open
A63: I6 | B63: What maximum take-off mass does the target regulatory class allow? | C63: kg | D63: Operating permits | E63: Rule | G63: 30 | H63: In Russia, UAVs up to 30 kg are in the registration-only class; above that, airworthiness certification is needed. | I63: Open
A64: J | B64: Economics (OAB-3: Invest in the service → Payment)
A65: J1 | B65: What is the maximum cost per delivery? | C65: RUB | D65: Payment (helicopter >1M, drone ~27k) | E65: Target | F65: ★ | G65: ≤ 30,000 | H65: Preliminary target for the average transport cost per completed delivery, excluding the medicine purchase price. Includes allocated operating costs and equipment depreciation. To be validated against mission distance, annual demand and supplier quotations. | I65: Open
A66: J2 | B66: What is the maximum capital cost of the system? | C66: RUB | D66: Invest in the service | E66: Target | G66: ≤ 15,000,000 | H66: Preliminary investment ceiling for the initial service configuration, including UAVs, medical containers, weather sensors, ground equipment and commissioning. Assumes the use of existing port infrastructure. Feasibility must be checked against the three simultaneous missions specified in A2 and the required coverage. | I66: Open
A67: J3 | B67: What is the maximum annual operating cost? | C67: RUB/year | D67: Payment | E67: Target | G67: ≤ 6,000,000 | H67: Preliminary annual operating budget covering allocated staff time, maintenance, batteries, communication, energy, insurance and consumables. Assumes shared facilities and personnel at existing sites. Equipment depreciation and medicine procurement are excluded. | I67: Open
A68: J4 | B68: What payback period is required? | C68: years | D68: Invest in the service | E68: Target | G68: ≤ 5 | H68: Proposed simple payback target. Payback must be calculated from the initial investment and annual net operating cash flow. The target requires validation of delivery tariffs, mission demand, operating costs and any public funding. | I68: Open
A69: J5 | B69: What is the maximum staff per base? | C69: persons | D69: Manage the service and procure supplies | E69: Target | G69: ≤ 2 on-duty persons per base | H69: Preliminary staffing target during an active mission: one operator or technician and one person responsible for package preparation and handling. Roles may be combined with existing port duties. Total staffing for continuous shift coverage must be determined separately. | I69: Open

Sheet Progress
A1: Progress by group
A3: Group | B3: Name | C3: Questions | D3: Answered | E3: Confirmed | F3: % answered
A4: A | B4: Demand and response time | C4: =COUNTA('NFR questions'!A6:A10) -> 5 | D4: =SUMPRODUCT(--(LEN('NFR questions'!G6:G10)>0)) -> 5 | E4: =COUNTIF('NFR questions'!I6:I10,"Confirmed") -> 0 | F4: =IF(C4=0,0,D4/C4) -> 1
A5: B | B5: Payload | C5: =COUNTA('NFR questions'!A12:A16) -> 5 | D5: =SUMPRODUCT(--(LEN('NFR questions'!G12:G16)>0)) -> 5 | E5: =COUNTIF('NFR questions'!I12:I16,"Confirmed") -> 0 | F5: =IF(C5=0,0,D5/C5) -> 1
A6: C | B6: Distance and coverage | C6: =COUNTA('NFR questions'!A18:A23) -> 6 | D6: =SUMPRODUCT(--(LEN('NFR questions'!G18:G23)>0)) -> 4 | E6: =COUNTIF('NFR questions'!I18:I23,"Confirmed") -> 0 | F6: =IF(C6=0,0,D6/C6) -> 0.66666667
A7: D | B7: Operating environment | C7: =COUNTA('NFR questions'!A25:A31) -> 7 | D7: =SUMPRODUCT(--(LEN('NFR questions'!G25:G31)>0)) -> 7 | E7: =COUNTIF('NFR questions'!I25:I31,"Confirmed") -> 0 | F7: =IF(C7=0,0,D7/C7) -> 1
A8: E | B8: Handover at the receiving site | C8: =COUNTA('NFR questions'!A33:A37) -> 5 | D8: =SUMPRODUCT(--(LEN('NFR questions'!G33:G37)>0)) -> 5 | E8: =COUNTIF('NFR questions'!I33:I37,"Confirmed") -> 0 | F8: =IF(C8=0,0,D8/C8) -> 1
A9: F | B9: Weather data | C9: =COUNTA('NFR questions'!A39:A45) -> 7 | D9: =SUMPRODUCT(--(LEN('NFR questions'!G39:G45)>0)) -> 7 | E9: =COUNTIF('NFR questions'!I39:I45,"Confirmed") -> 0 | F9: =IF(C9=0,0,D9/C9) -> 1
A10: G | B10: Monitoring and communication | C10: =COUNTA('NFR questions'!A47:A49) -> 3 | D10: =SUMPRODUCT(--(LEN('NFR questions'!G47:G49)>0)) -> 3 | E10: =COUNTIF('NFR questions'!I47:I49,"Confirmed") -> 0 | F10: =IF(C10=0,0,D10/C10) -> 1
A11: H | B11: Readiness and maintenance | C11: =COUNTA('NFR questions'!A51:A56) -> 6 | D11: =SUMPRODUCT(--(LEN('NFR questions'!G51:G56)>0)) -> 6 | E11: =COUNTIF('NFR questions'!I51:I56,"Confirmed") -> 0 | F11: =IF(C11=0,0,D11/C11) -> 1
A12: I | B12: Safety and regulation | C12: =COUNTA('NFR questions'!A58:A63) -> 6 | D12: =SUMPRODUCT(--(LEN('NFR questions'!G58:G63)>0)) -> 6 | E12: =COUNTIF('NFR questions'!I58:I63,"Confirmed") -> 0 | F12: =IF(C12=0,0,D12/C12) -> 1
A13: J | B13: Economics | C13: =COUNTA('NFR questions'!A65:A69) -> 5 | D13: =SUMPRODUCT(--(LEN('NFR questions'!G65:G69)>0)) -> 5 | E13: =COUNTIF('NFR questions'!I65:I69,"Confirmed") -> 0 | F13: =IF(C13=0,0,D13/C13) -> 1
B14: Total | C14: =SUM(C4:C13) -> 55 | D14: =SUM(D4:D13) -> 53 | E14: =SUM(E4:E13) -> 0 | F14: =IF(C14=0,0,D14/C14) -> 0.96363636
B16: Note: C4 is calculated, so it counts as answered once A4, A5 and E4 are filled.

Sheet Legend
A1: How to fill in this workbook
A3: Yellow cells | B3: The only cells to edit: Value, Source / justification and Status in the NFR questions sheet.
A4: Grey cell | B4: Calculated (C4 transit time). Do not type here.
A5: Value | B5: A number, or a range for things like temperature (e.g. −45 … +20). Use the unit in the Unit column.
A6: Source | B6: Where the number comes from: climate dataset, regulation, market report, customer interview. Without a source, the value is an assumption.
A7: Status | B7: Open = not answered · Assumed = your estimate, to check · Confirmed = backed by a source.
A8: Type | B8: Fact = look it up (environment) · Target = stakeholders decide · Rule = set by regulation · Derived = calculated from other answers.
A9: Key driver ★ | B9: Answer these eight first: A4, B1, C2, D1, D2, D7, E2, J1. They drive the whole design.
A10: Conflicts | B10: Some answers will conflict (e.g. high availability D7 vs low cost J1). Note it in Source; it is resolved in the LA/PA trade-off.
A12: Example row (format only) | B12: B1 | What is the maximum payload mass per delivery? | kg | Value: 2 | Source: typical emergency kit mass, assumption to check with FMBA | Status: Assumed
